lit_classifier/__init__.py
lit_classifier/_modidx.py
lit_classifier/all.py
lit_classifier/base_exp.py
lit_classifier/lit_model.py
lit_classifier/loss.py
lit_classifier/persistance.py
lit_classifier/trainer.py
lit_classifier-0.0.2.dist-info/LICENSE
lit_classifier-0.0.2.dist-info/METADATA
lit_classifier-0.0.2.dist-info/WHEEL
lit_classifier-0.0.2.dist-info/entry_points.txt
lit_classifier-0.0.2.dist-info/top_level.txt
lit_classifier-0.0.2.dist-info/RECORD
