Metadata-Version: 2.1
Name: lit-classifier
Version: 0.0.2
Summary: Wraper for pytorch lighining classification
Home-page: https://github.com/anhvth/lit_classifier/tree/main/
Author: anhvth
Author-email: anhvth.226@gmail.com
License: Apache Software License 2.0
Keywords: fast pytorch classifie builder
Platform: UNKNOWN
Classifier: Development Status :: 3 - Alpha
Classifier: Intended Audience :: Developers
Classifier: Natural Language :: English
Classifier: Programming Language :: Python :: 3.6
Classifier: Programming Language :: Python :: 3.7
Classifier: Programming Language :: Python :: 3.8
Classifier: Programming Language :: Python :: 3.9
Classifier: Programming Language :: Python :: 3.10
Classifier: License :: OSI Approved :: Apache Software License
Requires-Python: >=3.6
Requires-Dist: pip
Requires-Dist: packaging
Requires-Dist: timm
Requires-Dist: pytorch-lightning
Requires-Dist: loguru
Requires-Dist: mmcv
Requires-Dist: tabulate
Provides-Extra: dev
